{"Address":"1020 E. 14th Place","BuildingArea":"28,906","PrimaryUseType":"light manufacturing","Jurisdiction":"LADBS","Size":"Medium","Customer":"Jackie Alvarez","AuditLevel":"2","Audit Price":"$5,200.00"}
{"Address":"5500 W. 83rd St.","BuildingArea":"39,960","PrimaryUseType":"light manufacturing","Jurisdiction":"LADBS","Size":"Medium","Customer":"Jackie Alvarez","AuditLevel":"2","Audit Price":"$5,900.00"}
{"Address":"8414 Orion Avenue","BuildingArea":"76,200","PrimaryUseType":"apartments","Jurisdiction":"LADBS","Size":"Large","Customer":"Saxon Novotka","AuditLevel":"2","Audit Price":"$5,550.00"}
{"Address":"10511 Lindley Avenue","BuildingArea":"63,184","PrimaryUseType":"apartments","Jurisdiction":"LADBS","Size":"Large","Customer":"Saxon Novotka","AuditLevel":"2","Audit Price":"$5,000.00"}
{"Address":"1150 North Wilmington Boulevard","BuildingArea":"45,188","PrimaryUseType":"apartments","Jurisdiction":"LADBS","Size":"Medium","Customer":"Saxon Novotka","AuditLevel":"2","Audit Price":"$4,759.40"}
{"Address":"1500 East Lomita Boulevard","BuildingArea":"22,000","PrimaryUseType":"auto body repair","Jurisdiction":"LADBS","Size":"Small","Customer":"Saxon Novotka","AuditLevel":"2","Audit Price":"$4,000.00"}
{"Address":"561-581 Mateo Street","BuildingArea":"192,947","PrimaryUseType":"office","Jurisdiction":"LADBS","Size":"Extra Large","Customer":"Erika Hughes","AuditLevel":"2","Audit Price":"$12,000.00"}
{"Address":"705 West 9th Street","BuildingArea":"263,335","PrimaryUseType":"apartments","Jurisdiction":"LADBS","Size":"Extra Large","Customer":"Erika Hughes","AuditLevel":"2","Audit Price":"$15,000.00"}
{"Address":"1400 N Spring St","BuildingArea":"20,419","PrimaryUseType":"warehouse","Jurisdiction":"LADBS","Size":"Small","Customer":"Becki Ueno","AuditLevel":"2","Audit Price":"$4,000.00"}
{"Address":"400","BuildingArea":"38,401","PrimaryUseType":"retail","Jurisdiction":"LADBS","Size":"Medium","Customer":"Chad Choi","AuditLevel":"2","Audit Price":"$4,450.00"}
{"Address":"794 E 14TH Street","BuildingArea":"22,534","PrimaryUseType":"warehouse","Jurisdiction":"LADBS","Size":"Small","Customer":"Philip Kim","AuditLevel":"2","Audit Price":"$4,000.00"}
{"Address":"3050 E 11th St","BuildingArea":"42,400","PrimaryUseType":"food processing","Jurisdiction":"LADBS","Size":"Medium","Customer":"Cameron","AuditLevel":"2","Audit Price":"$6,250.00"}
{"Address":"16944 S Vermont Ave","BuildingArea":"41,810","PrimaryUseType":"light industrial","Jurisdiction":"LADBS","Size":"Medium","Customer":"Tim Hickock","AuditLevel":"2","Audit Price":"$5,350.00"}
{"Address":"21350 Lassen St","BuildingArea":"124,500","PrimaryUseType":"warehouse","Jurisdiction":"LADBS","Size":"Extra Large","Customer":"Kevin Petrovic","AuditLevel":"2","Audit Price":"$5,250.00"}
{"Address":"647 E 59th St","BuildingArea":"74,080","PrimaryUseType":"warehouse","Jurisdiction":"LADBS","Size":"Large","Customer":"Carlos Espinoza","AuditLevel":"2","Audit Price":"$4,250.00"}
{"Address":"112 W 52nd St","BuildingArea":"28,215","PrimaryUseType":"church","Jurisdiction":"LADBS","Size":"Medium","Customer":"Rodney Ross","AuditLevel":"2","Audit Price":"$4,000.00"}
{"Address":"610 E 59th St","BuildingArea":"47,705","PrimaryUseType":"light industrial","Jurisdiction":"LADBS","Size":"Medium","Customer":"Carlos Espinoza","AuditLevel":"2","Audit Price":"$6,000.00"}
{"Address":"611 E 59th St","BuildingArea":"34,128","PrimaryUseType":"warehouse","Jurisdiction":"LADBS","Size":"Medium","Customer":"Carlos Espinoza","AuditLevel":"2","Audit Price":"$4,750.00"}
{"Address":"1414 Greenfield Ave","BuildingArea":"40,573","PrimaryUseType":"apartments","Jurisdiction":"LADBS","Size":"Medium","Customer":"Ruth Goodman","AuditLevel":"2","Audit Price":"$5,000.00"}
{"Address":"3600 E. Olympic Blvd","BuildingArea":"138,268","PrimaryUseType":"manufacturing/warehouse","Jurisdiction":"LADBS","Size":"Extra Large","Customer":"Claudia","AuditLevel":"2","Audit Price":"$6,250.00"}
{"Address":"3434 W. 6th Street","BuildingArea":"26,550","PrimaryUseType":"office/retail","Jurisdiction":"LADBS","Size":"Small","Customer":"Claudia","AuditLevel":"2","Audit Price":"$4,750.00"}
{"Address":"21700 Septo St","BuildingArea":"20,000","PrimaryUseType":"apartments","Jurisdiction":"LADBS","Size":"Small","Customer":"Daniel Waterman","AuditLevel":"2","Audit Price":"$4,000.00"}
{"Address":"690 Veteran Ave","BuildingArea":"37,066","PrimaryUseType":"apartments","Jurisdiction":"LADBS","Size":"Medium","Customer":"Cristina","AuditLevel":"2","Audit Price":"$5,000.00"}
{"Address":"1919 3rd Ave","BuildingArea":"24,000","PrimaryUseType":"warehouse","Jurisdiction":"LADBS","Size":"Small","Customer":"Ricky","AuditLevel":"2","Audit Price":"$4,000.00"}
{"Address":"8841 Wilbur Ave.","BuildingArea":"23,978","PrimaryUseType":"industrial/office? (SF vs loopnet)","Jurisdiction":"LADBS","Size":"Small","Customer":"May Cohen","AuditLevel":"2","Audit Price":"$5,000.00"}
{"Address":"12110 Rochester Ave","BuildingArea":"26,199","PrimaryUseType":"apartments","Jurisdiction":"LADBS","Size":"Small","Customer":"Roger Cowan","AuditLevel":"2","Audit Price":"$5,000.00"}
{"Address":"12833 Ventura Blvd","BuildingArea":"95,000","PrimaryUseType":"retail","Jurisdiction":"LADBS","Size":"Large","Customer":"Demetrius Bradshaw","AuditLevel":"2","Audit Price":"$6,500.00"}
{"Address":"692-698 S Alvarado St","BuildingArea":"39,354","PrimaryUseType":"office","Jurisdiction":"LADBS","Size":"Medium","Customer":"Demetrius Bradshaw","AuditLevel":"2","Audit Price":"$5,000.00"}
{"Address":"2222 Figueroa St","BuildingArea":"86,633","PrimaryUseType":"office/retail/multi-family","Jurisdiction":"LADBS","Size":"Large","Customer":"Naseem Abofathi","AuditLevel":"2","Audit Price":"$5,990.00"}
{"Address":"7767 Hollywood Blvd","BuildingArea":"22,179","PrimaryUseType":"multi-family","Jurisdiction":"LADBS","Size":"Small","Customer":"Mike Resnick","AuditLevel":"2","Audit Price":"$4,500.00"}
{"Address":"8929 Oso Ave","BuildingArea":"23,232","PrimaryUseType":"industrial","Jurisdiction":"LADBS","Size":"Small","Customer":"David Johal","AuditLevel":"1","Audit Price":"$2,500.00"}
{"Address":"1922 E 7th Pl","BuildingArea":"22,000","PrimaryUseType":"industrial","Jurisdiction":"LADBS","Size":"Small","Customer":"Bahnjeet","AuditLevel":"2","Audit Price":"$5,000.00"}
{"Address":"1242 S BERENDO ST","BuildingArea":"36,252","PrimaryUseType":"Retail - one store","Jurisdiction":"LADBS","Size":"Medium","Customer":"Eddie Crespo","AuditLevel":"2","Audit Price":"$5,000.00"}
{"Address":"1200 S Club View Dr","BuildingArea":"164,901","PrimaryUseType":"Condos","Jurisdiction":"LADBS","Size":"Extra Large","Customer":"Angel Valdez","AuditLevel":"2","Audit Price":"$15,000.00"}
{"Address":"20746 (OLD) Dearborn St","BuildingArea":"21,450","PrimaryUseType":"Warehouse","Jurisdiction":"LADBS","Size":"Small","Customer":"Robert Fletcher","AuditLevel":"2","Audit Price":"$5,000.00"}
{"Address":"2203 3rd","BuildingArea":"33,998","PrimaryUseType":"industrial","Jurisdiction":"SF","Size":"Medium","Customer":"Melanie Myers","AuditLevel":"1","Audit Price":"$2,695.00"}
{"Address":"577 2nd","BuildingArea":"30,480","PrimaryUseType":"office","Jurisdiction":"SF","Size":"Medium","Customer":"Melanie Myers","AuditLevel":"1","Audit Price":"$2,395.00"}
{"Address":"128 King","BuildingArea":"46,500","PrimaryUseType":"office","Jurisdiction":"SF","Size":"Medium","Customer":"Ron Anderson","AuditLevel":"1","Audit Price":"$3,295.00"}
{"Address":"45 Kearny St","BuildingArea":"28,660","PrimaryUseType":"office","Jurisdiction":"SF","Size":"Medium","Customer":"Alex Ayala","AuditLevel":"1","Audit Price":"$2,695.00"}
{"Address":"165 Post St","BuildingArea":"46,314","PrimaryUseType":"office","Jurisdiction":"SF","Size":"Medium","Customer":"Alex Ayala","AuditLevel":"1","Audit Price":"$3,795.00"}
{"Address":"600 Alabama St","BuildingArea":"12,400","PrimaryUseType":"industrial/office? (SF vs loopnet)","Jurisdiction":"SF","Size":"Extra Small","Customer":"Dr. Jill Williamson","AuditLevel":"1","Audit Price":"$1,895.00"}
{"Address":"1438 Market St","BuildingArea":"23,260","PrimaryUseType":"office","Jurisdiction":"SF","Size":"Small","Customer":"Daniel Tavares","AuditLevel":"1","Audit Price":"$2,595.00"}
{"Address":"66 Potrero","BuildingArea":"159,678","PrimaryUseType":"Commercial/Warehouse/Office","Jurisdiction":"SF","Size":"Extra Large","Customer":"Byer California","AuditLevel":"2","Audit Price":"$4,500.00"}
{"Address":"545 Sutter","BuildingArea":"19,786","PrimaryUseType":"","Jurisdiction":"","Size":"Small","Customer":"Simon Chang","AuditLevel":"1","Audit Price":"$1,995.00"}
{"Address":"2489 Mission","BuildingArea":"16,996","PrimaryUseType":"","Jurisdiction":"","Size":"Extra Small","Customer":"Nidal Nazzal","AuditLevel":"1","Audit Price":"$2,395.00"}
{"Address":"175 De Haro","BuildingArea":"13,000","PrimaryUseType":"","Jurisdiction":"","Size":"Extra Small","Customer":"Joe Talmadge","AuditLevel":"1","Audit Price":"$1,795.00"}
{"Address":"1001 Brannan","BuildingArea":"26,000","PrimaryUseType":"commercial","Jurisdiction":"","Size":"Small","Customer":"Ron Anderson","AuditLevel":"1","Audit Price":"$1,895.00"}
{"Address":"929 Clay","BuildingArea":"58,726","PrimaryUseType":"","Jurisdiction":"","Size":"Large","Customer":"Deirdre Moy","AuditLevel":"2","Audit Price":"$4,295.00"}
{"Address":"2534 Mission St","BuildingArea":"15,300","PrimaryUseType":"","Jurisdiction":"","Size":"Extra Small","Customer":"John Clark","AuditLevel":"1","Audit Price":"$1,795.00"}
{"Address":"984 Folsom","BuildingArea":"22,240","PrimaryUseType":"","Jurisdiction":"","Size":"Small","Customer":"Taylor Lee","AuditLevel":"1","Audit Price":"$1,795.00"}
{"Address":"225 Hyde St","BuildingArea":"52,661","PrimaryUseType":"mixed use residential","Jurisdiction":"SF","Size":"Large","Customer":"Brandon Murphy","AuditLevel":"1","Audit Price":"$4,295.00"}
{"Address":"655-675 South Van Ness Ave","BuildingArea":"20,005","PrimaryUseType":"Commercia/Warehouse","Jurisdiction":"SF","Size":"Small","Customer":"Ken Tam","AuditLevel":"1","Audit Price":"$2,195.00"}
{"Address":"3175 17th St","BuildingArea":"14,400","PrimaryUseType":"Commercial/School","Jurisdiction":"SF","Size":"Extra Small","Customer":"Jason Dinneen","AuditLevel":"1","Audit Price":"$1,895.00"}
{"Address":"3655 LENAWEE AVE","BuildingArea":"23,100","PrimaryUseType":"Industrial","Jurisdiction":"LADBS","Size":"Small","Customer":"David Sostchen","AuditLevel":"2","Audit Price":"$4,500.00"}
{"Address":"1 Sutter Street/540 Market Street","BuildingArea":"34,265","PrimaryUseType":"Office","Jurisdiction":"SF","Size":"Medium","Customer":"CypressCapital (1 Sutter Street), Inc.","AuditLevel":"1","Audit Price":"$2,995.00"}
{"Address":"499 Jackson Street","BuildingArea":"17,911","PrimaryUseType":"Office","Jurisdiction":"SF","Size":"Small","Customer":"499 Jackson, LLC","AuditLevel":"1","Audit Price":"$2,395.00"}
{"Address":"4847 Laurel Canyon Blvd","BuildingArea":"28,806","PrimaryUseType":"Apartment","Jurisdiction":"LADBS","Size":"Medium","Customer":"LC Lofts LLC","AuditLevel":"2","Audit Price":"$5,000.00"}
{"Address":"6138 FRANKLIN AVE","BuildingArea":"142,785","PrimaryUseType":"Apartment","Jurisdiction":"LADBS","Size":"Extra Large","Customer":"Legacy Partners/Steven Yamamoto","AuditLevel":"2","Audit Price":"$12,000.00"}
{"Address":"225 Post St","BuildingArea":"17,000","PrimaryUseType":"Retail","Jurisdiction":"SF","Size":"Small","Customer":"Burberry","AuditLevel":"1","Audit Price":"$1,695.00"}
{"Address":"8201 Topanga Canyon Blvd","BuildingArea":"65,819","PrimaryUseType":"Supermarket/Grocery Store","Jurisdiction":"LADBS","Size":"Large","Customer":"Vallarta Supermarkets","AuditLevel":"2","Audit Price":"$7,800.00"}
{"Address":"13287 Ralston Ave","BuildingArea":"91,500","PrimaryUseType":"Supermarket/Grocery Store","Jurisdiction":"LADBS","Size":"Large","Customer":"Vallarta Supermarkets","AuditLevel":"2","Audit Price":"$7,800.00"}
{"Address":"16040 Sherman Way","BuildingArea":"40,625","PrimaryUseType":"Supermarket/Grocery Store","Jurisdiction":"LADBS","Size":"Medium","Customer":"Vallarta Supermarkets","AuditLevel":"2","Audit Price":"$5,340.00"}
{"Address":"13820 Foothill Blvd","BuildingArea":"33,000","PrimaryUseType":"Supermarket/Grocery Store","Jurisdiction":"LADBS","Size":"Medium","Customer":"Vallarta Supermarkets","AuditLevel":"2","Audit Price":"$5,340.00"}
{"Address":"10859 Oxnard St","BuildingArea":"20,799","PrimaryUseType":"Supermarket/Grocery Store","Jurisdiction":"LADBS","Size":"Small","Customer":"Vallarta Supermarkets","AuditLevel":"2","Audit Price":"$5,700.00"}
{"Address":"9533 W. Pico Blvd","BuildingArea":"24,155","PrimaryUseType":"Retail","Jurisdiction":"LADBS","Size":"Small","Customer":"Yanina Zajdman/E.M. Caplow Associates","AuditLevel":"2","Audit Price":"$4,900.00"}
{"Address":"630 S Spring St","BuildingArea":"86,850","PrimaryUseType":"Office","Jurisdiction":"LADBS","Size":"Large","Customer":"Marvin Buenaflor/MALDEF","AuditLevel":"2","Audit Price":"$6,500.00"}
{"Address":"9000 Mason Avenue","BuildingArea":"26,520","PrimaryUseType":"Light Industrial","Jurisdiction":"LADBS","Size":"Small","Customer":"Frank Spinale/Hydraulics International, Inc","AuditLevel":"2","Audit Price":"$5,400.00"}
{"Address":"20961 Knapp Street","BuildingArea":"44,299","PrimaryUseType":"Industrial/Manufacturing","Jurisdiction":"LADBS","Size":"Medium","Customer":"Frank Spinale/Hydraulics International, Inc","AuditLevel":"2","Audit Price":"$4,000.00"}
{"Address":"541 S Spring St","BuildingArea":"62,680","PrimaryUseType":"Mixed Use","Jurisdiction":"LADBS","Size":"Large","Customer":"Jacob Allen","AuditLevel":"2","Audit Price":"$4,450.00"}
{"Address":"4605 Lankershim Blvd","BuildingArea":"109,329","PrimaryUseType":"Office","Jurisdiction":"LADBS","Size":"Extra Large","Customer":"Thomas Von Der Ahe/VDA Property Company","AuditLevel":"2","Audit Price":"$7,700.00"}
{"Address":"3600 E. Olympic Blvd","BuildingArea":"138,268","PrimaryUseType":"manufacturing/warehouse","Jurisdiction":"LADBS","Size":"Extra Large","Customer":"Claudia","AuditLevel":"2","Audit Price":"$6,650.00"}
{"Address":"3434 W. 6th Street","BuildingArea":"26,550","PrimaryUseType":"office/retail","Jurisdiction":"LADBS","Size":"Small","Customer":"Claudia","AuditLevel":"2","Audit Price":"$4,750.00"}
{"Address":"5437 Harold Way","BuildingArea":"21,056","PrimaryUseType":"multi-family","Jurisdiction":"LADBS","Size":"Small","Customer":"Min Kim","AuditLevel":"2","Audit Price":"$4,500.00"}
{"Address":"17925 Devonshire St.","BuildingArea":"22,687","PrimaryUseType":"multi-family","Jurisdiction":"LADBS","Size":"Small","Customer":"Min Kim","AuditLevel":"2","Audit Price":"$4,500.00"}
{"Address":"12254 Burbank Blvd.","BuildingArea":"24,794","PrimaryUseType":"multi-family","Jurisdiction":"LADBS","Size":"Small","Customer":"Min Kim","AuditLevel":"2","Audit Price":"$4,500.00"}
{"Address":"8553 Sepulveda Blvd.","BuildingArea":"28,230","PrimaryUseType":"multi-family","Jurisdiction":"LADBS","Size":"Small","Customer":"Min Kim","AuditLevel":"2","Audit Price":"$4,500.00"}
{"Address":"15050 Parthenia St","BuildingArea":"32,296","PrimaryUseType":"multi-family","Jurisdiction":"LADBS","Size":"Medium","Customer":"Min Kim","AuditLevel":"2","Audit Price":"$5,250.00"}
{"Address":"1008 Rosemont Ave","BuildingArea":"33,191","PrimaryUseType":"multi-family","Jurisdiction":"LADBS","Size":"Medium","Customer":"Min Kim","AuditLevel":"2","Audit Price":"$5,250.00"}
{"Address":"2959 Leeward Ave","BuildingArea":"39,678","PrimaryUseType":"multi-family","Jurisdiction":"LADBS","Size":"Medium","Customer":"Min Kim","AuditLevel":"2","Audit Price":"$5,250.00"}
{"Address":"8437 Cedros Ave","BuildingArea":"40,089","PrimaryUseType":"multi-family","Jurisdiction":"LADBS","Size":"Medium","Customer":"Min Kim","AuditLevel":"2","Audit Price":"$6,000.00"}
{"Address":"7251 Milwood Ave","BuildingArea":"41,402","PrimaryUseType":"multi-family","Jurisdiction":"LADBS","Size":"Medium","Customer":"Min Kim","AuditLevel":"2","Audit Price":"$6,000.00"}
{"Address":"417 S Bonnie Brae St.","BuildingArea":"45,963","PrimaryUseType":"multi-family","Jurisdiction":"LADBS","Size":"Medium","Customer":"Min Kim","AuditLevel":"2","Audit Price":"$6,000.00"}
{"Address":"3240 W Slauson Ave","BuildingArea":"73,697","PrimaryUseType":"retail","Jurisdiction":"LADBS","Size":"Large","Customer":"Emerson Simpson","AuditLevel":"2","Audit Price":"$6,800.00"}
{"Address":"9727 DE SOTO AVE","BuildingArea":"210,386","PrimaryUseType":"Lightindustrial","Jurisdiction":"LADBS","Size":"Extra Large","Customer":"Christina Medlin/NHBB","AuditLevel":"2","Audit Price":"$12,500.00"}
{"Address":"508 Gulf Ave","BuildingArea":"24,280","PrimaryUseType":"multi-family","Jurisdiction":"LADBS","Size":"Small","Customer":"Min Kim","AuditLevel":"2","Audit Price":"$4,500.00"}
{"Address":"4821 Sepulveda Blvd","BuildingArea":"38,930","PrimaryUseType":"multi-family","Jurisdiction":"LADBS","Size":"Medium","Customer":"Michael Eastman","AuditLevel":"2","Audit Price":"$5,250.00"}
{"Address":"2024 W 6th St","BuildingArea":"45,147","PrimaryUseType":"Retail/Residential","Jurisdiction":"LADBS","Size":"Medium","Customer":"Yossi Engel/Countywide Management","AuditLevel":"2","Audit Price":"$5,550.00"}
{"Address":"2065 W 6th St","BuildingArea":"40,159","PrimaryUseType":"Retail/Residential","Jurisdiction":"LADBS","Size":"Medium","Customer":"Yossi Engel/Countywide Management","AuditLevel":"2","Audit Price":"$5,550.00"}
{"Address":"323 Geary St","BuildingArea":"50,993","PrimaryUseType":"Office","Jurisdiction":"SF","Size":"Large","Customer":"Josh Cort","AuditLevel":"2","Audit Price":"$4,100.00"}
{"Address":"15215 Keswick St","BuildingArea":"26,674","PrimaryUseType":"Industrial","Jurisdiction":"LADBS","Size":"Small","Customer":"Kay Zec","AuditLevel":"2","Audit Price":"$5,200.00"}
{"Address":"6651 Fallbrook Ave","BuildingArea":"161,565","PrimaryUseType":"Commercial/Retail","Jurisdiction":"LADBS","Size":"Extra Large","Customer":"April Sheffield","AuditLevel":"2","Audit Price":"$7,700.00"}
{"Address":"6605 Fallbrook Ave","BuildingArea":"40,991","PrimaryUseType":"Commercial/Retail","Jurisdiction":"LADBS","Size":"Medium","Customer":"April Sheffield","AuditLevel":"2","Audit Price":"$5,100.00"}
{"Address":"7615 N LANKERSHIM BLVD","BuildingArea":"24,445","PrimaryUseType":"Hotel","Jurisdiction":"LADBS","Size":"Small","Customer":"Ruela Sabado","AuditLevel":"2","Audit Price":"$4,750.00"}
{"Address":"1100 S FLOWER ST","BuildingArea":"66,150","PrimaryUseType":"Office","Jurisdiction":"LADBS","Size":"Large","Customer":"Yassi Hariri","AuditLevel":"2","Audit Price":"$6,075.00"}
{"Address":"1111 S Hope St","BuildingArea":"186,610","PrimaryUseType":"Parking/commercial","Jurisdiction":"LADBS","Size":"Extra Large","Customer":"Yassi Hariri","AuditLevel":"2","Audit Price":"$8,550.00"}
{"Address":"400 2nd St","BuildingArea":"88,409","PrimaryUseType":"Office","Jurisdiction":"SF","Size":"Large","Customer":"Lisa Weadon","AuditLevel":"2","Audit Price":"$4,950.00"}
{"Address":"645 Harrison St","BuildingArea":"74,641","PrimaryUseType":"Office","Jurisdiction":"SF","Size":"Large","Customer":"Lisa Weadon","AuditLevel":"2","Audit Price":"$4,200.00"}
{"Address":"433 California St","BuildingArea":"108,925","PrimaryUseType":"Office","Jurisdiction":"SF","Size":"Extra Large","Customer":"Lisa Weadon","AuditLevel":"2","Audit Price":"$6,025.00"}
{"Address":"4751 Fountain Ave","BuildingArea":"93,990","PrimaryUseType":"Religious building","Jurisdiction":"LADBS","Size":"Large","Customer":"Kreg Laughlin","AuditLevel":"2","Audit Price":"$5,975.00"}
{"Address":"214 E 8th St","BuildingArea":"43,136","PrimaryUseType":"Light industrial","Jurisdiction":"LADBS","Size":"Medium","Customer":"Joanne Song","AuditLevel":"2","Audit Price":"$5,575.00"}
{"Address":"1560 S Centinela Ave","BuildingArea":"20,863","PrimaryUseType":"multi-family","Jurisdiction":"LADBS","Size":"Small","Customer":"Anastasia Tsitsishvili","AuditLevel":"2","Audit Price":"$4,500.00"}
{"Address":"1400 N Spring St","BuildingArea":"20,419","PrimaryUseType":"warehouse","Jurisdiction":"LADBS","Size":"Small","Customer":"Becki Ueno","AuditLevel":"2","Audit Price":"$4,500.00"}
{"Address":"1090 Sansome St","BuildingArea":"62,500","PrimaryUseType":"Office","Jurisdiction":"SF","Size":"Large","Customer":"Noe de la Cruz","AuditLevel":"2","Audit Price":"$4,595.00"}
{"Address":"4833 Fountain Ave","BuildingArea":"210,966","PrimaryUseType":"Religious","Jurisdiction":"LADBS","Size":"Extra Large","Customer":"Kreg Laughlin","AuditLevel":"2","Audit Price":"$11,225.00"}
{"Address":"4820 Fountain Ave","BuildingArea":"90,877","PrimaryUseType":"Parking garage","Jurisdiction":"LADBS","Size":"Large","Customer":"Kreg Laughlin","AuditLevel":"2","Audit Price":"$5,050.00"}
{"Address":"1825 N Bronson Ave","BuildingArea":"23,864","PrimaryUseType":"multi-family","Jurisdiction":"LADBS","Size":"Small","Customer":"Kreg Laughlin","AuditLevel":"2","Audit Price":"$5,100.00"}
{"Address":"15909 VANOWEN ST","BuildingArea":"20,048","PrimaryUseType":"multi-family","Jurisdiction":"LADBS","Size":"Small","Customer":"Tess Luna","AuditLevel":"2","Audit Price":"$4,750.00"}
{"Address":"14641 Delano St","BuildingArea":"20,526","PrimaryUseType":"multi-family","Jurisdiction":"LADBS","Size":"Small","Customer":"Tess Luna","AuditLevel":"2","Audit Price":"$4,750.00"}
{"Address":"8857 Cedros Ave","BuildingArea":"22,486","PrimaryUseType":"multi-family","Jurisdiction":"LADBS","Size":"Small","Customer":"Tess Luna","AuditLevel":"2","Audit Price":"$5,450.00"}
{"Address":"8630 Willis Ave ","BuildingArea":"28,388","PrimaryUseType":"multi-family","Jurisdiction":"LADBS","Size":"Medium","Customer":"Tess Luna","AuditLevel":"2","Audit Price":"$5,450.00"}
{"Address":"13349 Saticoy St","BuildingArea":"33,838","PrimaryUseType":"multi-family","Jurisdiction":"LADBS","Size":"Medium","Customer":"Tess Luna","AuditLevel":"2","Audit Price":"$5,900.00"}
{"Address":"14541 Victory Blvd","BuildingArea":"46,924","PrimaryUseType":"Office","Jurisdiction":"LADBS","Size":"Medium","Customer":"Tess Luna","AuditLevel":"2","Audit Price":"$6,500.00"}
{"Address":"1747 N NORMANDIE AVE","BuildingArea":"22,337","PrimaryUseType":"multi-family","Jurisdiction":"LADBS","Size":"Small","Customer":"Estrella Perez","AuditLevel":"2","Audit Price":"$4,650.00"}
{"Address":"1805 SICHEL ST","BuildingArea":"27,660","PrimaryUseType":"multi-family","Jurisdiction":"LADBS","Size":"Medium","Customer":"Estrella Perez","AuditLevel":"2","Audit Price":"$4,650.00"}
{"Address":"2250 E 111TH ST","BuildingArea":"112,213","PrimaryUseType":"multi-family","Jurisdiction":"LADBS","Size":"Extra Large","Customer":"Estrella Perez","AuditLevel":"2","Audit Price":"$9,750.00"}
{"Address":"7926 Foothill Blvd","BuildingArea":"22,282","PrimaryUseType":"multi-family","Jurisdiction":"LADBS","Size":"Small","Customer":"Saxon Nowotka","AuditLevel":"2","Audit Price":"$4,650.00"}
{"Address":"10825 Nettleton St","BuildingArea":"52,373","PrimaryUseType":"multi-family","Jurisdiction":"LADBS","Size":"Large","Customer":"Saxon Nowotka","AuditLevel":"2","Audit Price":"$5,700.00"}
{"Address":"307 S Reno St ","BuildingArea":"102,336","PrimaryUseType":"multi-family","Jurisdiction":"LADBS","Size":"Extra Large","Customer":"Saxon Nowotka","AuditLevel":"2","Audit Price":"$9,000.00"}
{"Address":"23200 Western Ave","BuildingArea":"115,449","PrimaryUseType":"multi-family","Jurisdiction":"LADBS","Size":"Extra Large","Customer":"Saxon Nowotka","AuditLevel":"2","Audit Price":"$9,750.00"}
{"Address":"1200 Wilshire Blvd","BuildingArea":"104,696","PrimaryUseType":"Office","Jurisdiction":"LADBS","Size":"Extra Large","Customer":"Edwin Martinez","AuditLevel":"2","Audit Price":"$7,700.00"}
{"Address":"300 W AVENUE 33","BuildingArea":"153,651","PrimaryUseType":"warehouse","Jurisdiction":"LADBS","Size":"Extra Large","Customer":"Gary Marion","AuditLevel":"2","Audit Price":"$7,250.00"}
{"Address":"827 Hyde St","BuildingArea":"21,607","PrimaryUseType":"Office","Jurisdiction":"SF","Size":"Small","Customer":"Weiya Noble","AuditLevel":"1","Audit Price":"$2,500.00"}
{"Address":"1697 PACIFIC AVE","BuildingArea":"68,757","PrimaryUseType":"Hotel","Jurisdiction":"LADBS","Size":"Large","Customer":"Ken Pratt","AuditLevel":"2","Audit Price":"$6,000.00"}
{"Address":"19310 PACIFIC GATEWAY DR","BuildingArea":"136,694","PrimaryUseType":"Warehouse","Jurisdiction":"LADBS","Size":"Extra Large","Customer":"Rob Decker","AuditLevel":"2","Audit Price":"$7,250.00"}
{"Address":"7600 LAUREL CANYON BLVD","BuildingArea":"57,883","PrimaryUseType":"Commercial/Retail","Jurisdiction":"LADBS","Size":"Large","Customer":"Lovine Gopez","AuditLevel":"2","Audit Price":"$6,300.00"}
{"Address":"425 S Palos Verdes St","BuildingArea":"30,193","PrimaryUseType":"Federal property/office","Jurisdiction":"LADBS","Size":"Medium","Customer":"Milind Desai","AuditLevel":"2","Audit Price":"$6,000.00"}
{"Address":"20600 Prairie St","BuildingArea":"64,751","PrimaryUseType":"Light industrial","Jurisdiction":"LADBS","Size":"Large","Customer":"Rodrigo Barragan","AuditLevel":"2","Audit Price":"$7,400.00"}
{"Address":"20630 PLUMMER ST","BuildingArea":"37,940","PrimaryUseType":"Light industrial","Jurisdiction":"LADBS","Size":"Medium","Customer":"Nancy / Striks Properties, LP","AuditLevel":"2","Audit Price":"$5,100.00"}
{"Address":"4845 Exposition Blvd","BuildingArea":"22,050","PrimaryUseType":"Light Manufacturing","Jurisdiction":"LADBS","Size":"Small","Customer":"Bernard Sichel","AuditLevel":"2","Audit Price":"$5,200.00"}
{"Address":"15600 Roxford St","BuildingArea":"144,630","PrimaryUseType":"Light industrial","Jurisdiction":"LADBS","Size":"Extra Large","Customer":"Jessie Lopez","AuditLevel":"ASHREA II","Audit Price":"$10,250.00"}
{"Address":"17830 Lassen St","BuildingArea":"26,424","PrimaryUseType":"multi-family","Jurisdiction":"LADBS","Size":"Small","Customer":"Ralice Remy","AuditLevel":"ASHREA II","Audit Price":"$4,650.00"}
{"Address":"13432 S. Vermont Avenue","BuildingArea":"20,058","PrimaryUseType":"multi-family","Jurisdiction":"LADBS","Size":"Small","Customer":"Ofelia Palma","AuditLevel":"2","Audit Price":"$4,650.00"}
{"Address":"6819 Hinds Ave","BuildingArea":"22,492","PrimaryUseType":"multi-family","Jurisdiction":"LADBS","Size":"Small","Customer":"Karina Rojas","AuditLevel":"2","Audit Price":"$4,650.00"}
{"Address":"820 S Mansfield Ave","BuildingArea":"22,920","PrimaryUseType":"multi-family","Jurisdiction":"LADBS","Size":"Small","Customer":"Michael LeBeau (Barcelona Apartments LP)","AuditLevel":"2","Audit Price":"$4,650.00"}
{"Address":"8631 STANMOOR DR","BuildingArea":"23,389","PrimaryUseType":"Religious","Jurisdiction":"LADBS","Size":"Small","Customer":"Fred Balsz","AuditLevel":"2","Audit Price":"$4,700.00"}
{"Address":"1845 Gramercy Pl","BuildingArea":"25,460","PrimaryUseType":"multi-family","Jurisdiction":"LADBS","Size":"Small","Customer":"Gidon Rosman","AuditLevel":"2","Audit Price":"$4,650.00"}
{"Address":"11265 Palms Blvd","BuildingArea":"25,688","PrimaryUseType":"multi-family","Jurisdiction":"LADBS","Size":"Small","Customer":"Karina Rojas","AuditLevel":"2","Audit Price":"$4,650.00"}
{"Address":"17433 VANOWEN ST","BuildingArea":"28,288","PrimaryUseType":"multi-family","Jurisdiction":"LADBS","Size":"Medium","Customer":"Gidon Rosman","AuditLevel":"2","Audit Price":"$4,650.00"}
{"Address":"508 S Serrano Ave","BuildingArea":"28,432","PrimaryUseType":"multi-family","Jurisdiction":"LADBS","Size":"Medium","Customer":"Michael LeBeau (Affordable Apartments I LP)","AuditLevel":"2","Audit Price":"$4,650.00"}
{"Address":"3742 Jasmine Ave","BuildingArea":"29,388","PrimaryUseType":"multi-family","Jurisdiction":"LADBS","Size":"Medium","Customer":"Michael LeBeau","AuditLevel":"2","Audit Price":"$4,650.00"}
{"Address":"7521 Simpson Ave","BuildingArea":"32,166","PrimaryUseType":"multi-family","Jurisdiction":"LADBS","Size":"Medium","Customer":"Karina Rojas","AuditLevel":"2","Audit Price":"$5,000.00"}
{"Address":"12309 Osborne Place","BuildingArea":"32,444","PrimaryUseType":"multi-family","Jurisdiction":"LADBS","Size":"Medium","Customer":"Marilu Vargas","AuditLevel":"2","Audit Price":"$5,000.00"}
{"Address":"5920 Melrose Avenue","BuildingArea":"33,012","PrimaryUseType":"multi-family","Jurisdiction":"LADBS","Size":"Medium","Customer":"Gloria Diaz","AuditLevel":"2","Audit Price":"$5,000.00"}
{"Address":"3760 Dufresne Ct","BuildingArea":"33,237","PrimaryUseType":"multi-family","Jurisdiction":"LADBS","Size":"Medium","Customer":"Karina Rojas","AuditLevel":"2","Audit Price":"$5,000.00"}
{"Address":"18331 Kittridge St","BuildingArea":"33,924","PrimaryUseType":"multi-family","Jurisdiction":"LADBS","Size":"Medium","Customer":"Melizza","AuditLevel":"2","Audit Price":"$5,000.00"}
{"Address":"8529 Willis Ave","BuildingArea":"38,137","PrimaryUseType":"multi-family","Jurisdiction":"LADBS","Size":"Medium","Customer":"Karina Rojas","AuditLevel":"2","Audit Price":"$5,000.00"}
{"Address":"1825 N CHEROKEE AVE","BuildingArea":"42,945","PrimaryUseType":"multi-family","Jurisdiction":"LADBS","Size":"Medium","Customer":"Tiffany Addison","AuditLevel":"2","Audit Price":"$5,350.00"}
{"Address":"5301 Newcastle Avenue","BuildingArea":"46,472","PrimaryUseType":"multi-family","Jurisdiction":"LADBS","Size":"Medium","Customer":"Gloria Diaz","AuditLevel":"2","Audit Price":"$5,350.00"}
{"Address":"14737 Sherman Way","BuildingArea":"49,263","PrimaryUseType":"multi-family","Jurisdiction":"LADBS","Size":"Medium","Customer":"Karina Rojas","AuditLevel":"2","Audit Price":"$5,350.00"}
{"Address":"18711 Ventura Blvd","BuildingArea":"44,885","PrimaryUseType":"Commercial","Jurisdiction":"LADBS","Size":"Medium","Customer":"Janice Lohman","AuditLevel":"2","Audit Price":"$5,675.00"}
{"Address":"12582 W Millennium","BuildingArea":"65,775","PrimaryUseType":"Office","Jurisdiction":"LADBS","Size":"Large","Customer":"Jay Banks","AuditLevel":"2","Audit Price":"$6,600.00"}
{"Address":"7360 LAUREL CANYON BLVD","BuildingArea":"58,640","PrimaryUseType":"Industrial","Jurisdiction":"LADBS","Size":"Large","Customer":"Courtney Cole","AuditLevel":"2","Audit Price":"$7,000.00"}
{"Address":"10303 NORRIS AVE","BuildingArea":"62,588","PrimaryUseType":"warehouse","Jurisdiction":"LADBS","Size":"Large","Customer":"Jeanine Tawil","AuditLevel":"2","Audit Price":"$5,475.00"}
{"Address":"17351 VANOWEN ST","BuildingArea":"37,134","PrimaryUseType":"multi-family","Jurisdiction":"LADBS","Size":"Medium","Customer":"Roberta Weiser","AuditLevel":"2","Audit Price":"$5,000.00"}
{"Address":"269 Loma Dr","BuildingArea":"24,830","PrimaryUseType":"multi-family","Jurisdiction":"LADBS","Size":"Small","Customer":"Esmeralda Rivera / New Capital LLC","AuditLevel":"2","Audit Price":"$4,650.00"}
{"Address":"375 S Columbia Ave","BuildingArea":"29,350","PrimaryUseType":"multi-family","Jurisdiction":"LADBS","Size":"Medium","Customer":"Esmeralda Rivera / New Capital LLC","AuditLevel":"2","Audit Price":"$4,650.00"}
{"Address":"4651 HUNTINGTON DR N","BuildingArea":"39,233","PrimaryUseType":"multi-family","Jurisdiction":"LADBS","Size":"Medium","Customer":"Esmeralda Rivera / New Capital LLC","AuditLevel":"2","Audit Price":"$5,000.00"}
{"Address":"421 S Bixel St","BuildingArea":"46,992","PrimaryUseType":"multi-family","Jurisdiction":"LADBS","Size":"Medium","Customer":"Esmeralda Rivera / New Capital LLC","AuditLevel":"2","Audit Price":"$5,350.00"}
{"Address":"142 W Santa Cruz St","BuildingArea":"62,079","PrimaryUseType":"multi-family","Jurisdiction":"LADBS","Size":"Large","Customer":"Esmeralda Rivera / New Capital LLC","AuditLevel":"2","Audit Price":"$6,000.00"}
{"Address":"201 N Beacon St","BuildingArea":"67,761","PrimaryUseType":"multi-family","Jurisdiction":"LADBS","Size":"Large","Customer":"Esmeralda Rivera / New Capital LLC","AuditLevel":"2","Audit Price":"$6,000.00"}
{"Address":"345 Columbia Ave","BuildingArea":"113,213","PrimaryUseType":"multi-family","Jurisdiction":"LADBS","Size":"Extra Large","Customer":"Esmeralda Rivera / New Capital LLC","AuditLevel":"2","Audit Price":"$9,750.00"}
{"Address":"7500 Alabama Ave","BuildingArea":"138,161","PrimaryUseType":"multi-family","Jurisdiction":"LADBS","Size":"Extra Large","Customer":"Esmeralda Rivera / New Capital LLC","AuditLevel":"2","Audit Price":"$11,250.00"}
{"Address":"20234 Roscoe Blvd.","BuildingArea":"24,176","PrimaryUseType":"multi-family","Jurisdiction":"LADBS","Size":"Small","Customer":"Estrella Perez / Solari Enterprises, Inc.","AuditLevel":"2","Audit Price":"$4,650.00"}
{"Address":"6016 Echo st","BuildingArea":"25,987","PrimaryUseType":"multi-family","Jurisdiction":"LADBS","Size":"Small","Customer":"Estrella Perez / Solari Enterprises, Inc.","AuditLevel":"2","Audit Price":"$4,650.00"}
{"Address":"7250 Hazeltine Ave.","BuildingArea":"31,930","PrimaryUseType":"multi-family","Jurisdiction":"LADBS","Size":"Medium","Customer":"Estrella Perez / Solari Enterprises, Inc.","AuditLevel":"2","Audit Price":"$5,000.00"}
{"Address":"1530 W. Jefferson Blvd","BuildingArea":"56,678","PrimaryUseType":"multi-family","Jurisdiction":"LADBS","Size":"Large","Customer":"Estrella Perez / Solari Enterprises, Inc.","AuditLevel":"2","Audit Price":"$5,700.00"}
{"Address":"2330 South Santa Ana Blvd.","BuildingArea":"56,694","PrimaryUseType":"multi-family","Jurisdiction":"LADBS","Size":"Large","Customer":"Estrella Perez / Solari Enterprises, Inc.","AuditLevel":"2","Audit Price":"$5,700.00"}
{"Address":"722 E. Washington Blvd.","BuildingArea":"67,182","PrimaryUseType":"multi-family","Jurisdiction":"LADBS","Size":"Large","Customer":"Estrella Perez / Solari Enterprises, Inc.","AuditLevel":"2","Audit Price":"$6,000.00"}
{"Address":"1011 E. Adams Blvd.","BuildingArea":"82,412","PrimaryUseType":"multi-family/mixed use","Jurisdiction":"LADBS","Size":"Large","Customer":"Estrella Perez / Solari Enterprises, Inc.","AuditLevel":"2","Audit Price":"$7,500.00"}
{"Address":"14630 Wyandotte Street","BuildingArea":"86,236","PrimaryUseType":"multi-family","Jurisdiction":"LADBS","Size":"Large","Customer":"Estrella Perez / Solari Enterprises, Inc.","AuditLevel":"2","Audit Price":"$7,500.00"}
{"Address":"426 S Sepulveda Blvd","BuildingArea":"46,501","PrimaryUseType":"multi-family","Jurisdiction":"LADBS","Size":"Medium","Customer":"Ada Wehbe","AuditLevel":"2","Audit Price":"$5,350.00"}
{"Address":"316 S Westlake Ave","BuildingArea":"24,646","PrimaryUseType":"hospital/private","Jurisdiction":"LADBS","Size":"Small","Customer":"Emma Perez / Westlake Convalescent Hospital","AuditLevel":"2","Audit Price":"$5,500.00"}
{"Address":"665 3rd St","BuildingArea":"134,445","PrimaryUseType":"Commercial","Jurisdiction":"SF","Size":"Extra Large","Customer":"Michelle Sung","AuditLevel":"2","Audit Price":"$6,700.00"}
{"Address":"14959 Vanowen St","BuildingArea":"21,700","PrimaryUseType":"multi-family","Jurisdiction":"LADBS","Size":"","Customer":"Melizza/LA Apartments","AuditLevel":"2","Audit Price":"$4,650.00"}
{"Address":"1150 N Normandie Ave","BuildingArea":"21,841","PrimaryUseType":"multi-family","Jurisdiction":"LADBS","Size":"","Customer":"Amanda Bernasconi","AuditLevel":"2","Audit Price":"$4,650.00"}
{"Address":"12332 Osborne Pl","BuildingArea":"22,848","PrimaryUseType":"multi-family","Jurisdiction":"LADBS","Size":"","Customer":"Melizza/LA Apartments","AuditLevel":"2","Audit Price":"$4,650.00"}
{"Address":"10133 Tabor St","BuildingArea":"23,304","PrimaryUseType":"multi-family","Jurisdiction":"LADBS","Size":"","Customer":"Erica Shellem","AuditLevel":"2","Audit Price":"$4,650.00"}
{"Address":"14137 Vanowen St","BuildingArea":"23,946","PrimaryUseType":"multi-family","Jurisdiction":"LADBS","Size":"","Customer":"Melizza/LA Apartments","AuditLevel":"2","Audit Price":"$4,650.00"}
{"Address":"1546 Gordon St","BuildingArea":"24,747","PrimaryUseType":"multi-family","Jurisdiction":"LADBS","Size":"","Customer":"Terri Roux","AuditLevel":"2","Audit Price":"$4,650.00"}
{"Address":"11919 Culver Blvd","BuildingArea":"24,805","PrimaryUseType":"multi-family","Jurisdiction":"LADBS","Size":"","Customer":"Erica Shellem","AuditLevel":"2","Audit Price":"$4,650.00"}
{"Address":"12225 Riverside Dr","BuildingArea":"25,385","PrimaryUseType":"multi-family","Jurisdiction":"LADBS","Size":"","Customer":"Melizza/LA Apartments","AuditLevel":"2","Audit Price":"$4,650.00"}
{"Address":"18414 Collins St","BuildingArea":"27,262","PrimaryUseType":"multi-family","Jurisdiction":"LADBS","Size":"","Customer":"Melizza/LA Apartments","AuditLevel":"2","Audit Price":"$4,650.00"}
{"Address":"20200 Leadwell St","BuildingArea":"27,552","PrimaryUseType":"multi-family","Jurisdiction":"LADBS","Size":"","Customer":"Melizza/LA Apartments","AuditLevel":"2","Audit Price":"$4,650.00"}
{"Address":"15537 Nordhoff St","BuildingArea":"27,879","PrimaryUseType":"multi-family","Jurisdiction":"LADBS","Size":"","Customer":"Amanda Bernasconi","AuditLevel":"2","Audit Price":"$4,650.00"}
{"Address":"21827 Lanark St","BuildingArea":"31,346","PrimaryUseType":"multi-family","Jurisdiction":"LADBS","Size":"","Customer":"Amanda Bernasconi","AuditLevel":"2","Audit Price":"$5,000.00"}
{"Address":"18317 Kittridge St","BuildingArea":"33,794","PrimaryUseType":"multi-family","Jurisdiction":"LADBS","Size":"","Customer":"Melizza/LA Apartments","AuditLevel":"2","Audit Price":"$5,000.00"}
{"Address":"14610 Plummer","BuildingArea":"34,300","PrimaryUseType":"multi-family","Jurisdiction":"LADBS","Size":"","Customer":"Melizza/LA Apartments","AuditLevel":"2","Audit Price":"$5,000.00"}
{"Address":"14411 Kittridge St","BuildingArea":"67,161","PrimaryUseType":"multi-family","Jurisdiction":"LADBS","Size":"","Customer":"Melizza/LA Apartments","AuditLevel":"2","Audit Price":"$6,000.00"}
{"Address":"14155 Magnolia Blvd","BuildingArea":"174,114","PrimaryUseType":"multi-family","Jurisdiction":"LADBS","Size":"","Customer":"Monica Heidt","AuditLevel":"2","Audit Price":"$12,000.00"}
{"Address":"6717 LELAND WAY","BuildingArea":"20,672","PrimaryUseType":"multi-family","Jurisdiction":"LADBS","Size":"","Customer":"Melizza/LA Apartments","AuditLevel":"2","Audit Price":"$4,650.00"}
{"Address":"860 S. Wooster Street","BuildingArea":"21,640","PrimaryUseType":"multi-family","Jurisdiction":"LADBS","Size":"","Customer":"Mo Funk","AuditLevel":"2","Audit Price":"$4,650.00"}
{"Address":"3339 S Canfield Ave","BuildingArea":"25,000","PrimaryUseType":"multi-family","Jurisdiction":"LADBS","Size":"","Customer":"Erica Shellem","AuditLevel":"2","Audit Price":"$4,650.00"}
{"Address":"530 S KENMORE AVE","BuildingArea":"26,896","PrimaryUseType":"multi-family","Jurisdiction":"LADBS","Size":"","Customer":"Tiffany Addison","AuditLevel":"2","Audit Price":"$4,650.00"}
{"Address":"611 S Normandie Ave","BuildingArea":"30,853","PrimaryUseType":"multi-family","Jurisdiction":"LADBS","Size":"","Customer":"Gidon Rosman","AuditLevel":"2","Audit Price":"$5,000.00"}
{"Address":"8926 Orion Ave","BuildingArea":"33,348","PrimaryUseType":"multi-family","Jurisdiction":"LADBS","Size":"","Customer":"Melizza/LA Apartments","AuditLevel":"2","Audit Price":"$5,000.00"}
{"Address":"5738 Carlton Way","BuildingArea":"33,516","PrimaryUseType":"multi-family","Jurisdiction":"LADBS","Size":"","Customer":"Nathan Korman","AuditLevel":"2","Audit Price":"$5,000.00"}
{"Address":"303 S Ave 57","BuildingArea":"34,420","PrimaryUseType":"multi-family","Jurisdiction":"LADBS","Size":"","Customer":"Melizza/LA Apartments","AuditLevel":"2","Audit Price":"$5,000.00"}
{"Address":"3623 Jasmine Ave","BuildingArea":"41,181","PrimaryUseType":"multi-family","Jurisdiction":"LADBS","Size":"","Customer":"Erica Shellem","AuditLevel":"2","Audit Price":"$5,350.00"}
{"Address":"310 S Almont St","BuildingArea":"55,915","PrimaryUseType":"multi-family","Jurisdiction":"LADBS","Size":"","Customer":"Moishe Simons","AuditLevel":"2","Audit Price":"$5,700.00"}
{"Address":"755 Sansome St","BuildingArea":"61,942","PrimaryUseType":"Office","Jurisdiction":"SF","Size":"","Customer":"Anya","AuditLevel":"2","Audit Price":"$4,595.00"}
{"Address":"20746 Dearborn St","BuildingArea":"21,450","PrimaryUseType":"Warehouse","Jurisdiction":"LADBS","Size":"Small","Customer":"Robert Fletcher","AuditLevel":"2","Audit Price":"$2,875.00"}
{"Address":"21721 Vanowen St","BuildingArea":"28,190","PrimaryUseType":"Commercial/Retail","Jurisdiction":"LADBS","Size":"","Customer":"Richard Massoth","AuditLevel":"2","Audit Price":"$5,225.00"}
{"Address":"6646 HOLLYWOOD BLVD","BuildingArea":"30,000","PrimaryUseType":"Commercial/Retail","Jurisdiction":"LADBS","Size":"","Customer":"cherilyn amber","AuditLevel":"2","Audit Price":"$5,450.00"}
{"Address":"225 26TH ST","BuildingArea":"25,774","PrimaryUseType":"Commercial/Retail","Jurisdiction":"LADBS","Size":"","Customer":"Cindy McAfee","AuditLevel":"2","Audit Price":"$5,225.00"}
{"Address":"5701 W CENTURY BLVD","BuildingArea":"562,856","PrimaryUseType":"Parking structure","Jurisdiction":"LADBS","Size":"Extra Large","Customer":"John Conway","AuditLevel":"2","Audit Price":"$19,675.00"}
{"Address":"261 S Kingsley","BuildingArea":"37,567","PrimaryUseType":"Office","Jurisdiction":"LADBS","Size":"","Customer":"Natalie Seo","AuditLevel":"2","Audit Price":"$5,550.00"}
{"Address":"2520 W 8TH ST","BuildingArea":"21,554","PrimaryUseType":"Commercial/Retail","Jurisdiction":"LADBS","Size":"","Customer":"Doo Hyung Kang / JL Restaurant Management","AuditLevel":"2","Audit Price":"$5,225.00"}
{"Address":"4240 LAUREL CANYON BLVD ","BuildingArea":"78,800","PrimaryUseType":"multi-family","Jurisdiction":"LADBS","Size":"","Customer":"Jan Moshier","AuditLevel":"2","Audit Price":"$6,750.00"}
{"Address":"836 Moraga Dr","BuildingArea":"21,600","PrimaryUseType":"multi-family","Jurisdiction":"LADBS","Size":"","Customer":"Patricia Lyons","AuditLevel":"2","Audit Price":"$4,650.00"}
{"Address":"1226 E 7TH ST","BuildingArea":"42,052","PrimaryUseType":"Hotel","Jurisdiction":"LADBS","Size":"","Customer":"Sy Rolnick","AuditLevel":"2","Audit Price":"$5,350.00"}
{"Address":"8701 Bellanca Ave","BuildingArea":"59,846","PrimaryUseType":"warehouse","Jurisdiction":"LADBS","Size":"","Customer":"Chris Schultz","AuditLevel":"2","Audit Price":"$5,475.00"}
{"Address":"607 S HILL ST","BuildingArea":"144,246","PrimaryUseType":"Office","Jurisdiction":"LADBS","Size":"","Customer":"Maria Tandoy","AuditLevel":"2","Audit Price":"$9,400.00"}
{"Address":"1500 E Lomita Blvd","BuildingArea":"22,000","PrimaryUseType":"auto body repair","Jurisdiction":"LADBS","Size":"","Customer":"Saxon Nowotka","AuditLevel":"2","Audit Price":"$4,500.00"}
{"Address":"700 W 58th St","BuildingArea":"20,853","PrimaryUseType":"Commercial","Jurisdiction":"LADBS","Size":"","Customer":"Fred Labib","AuditLevel":"2","Audit Price":"$5,225.00"}
{"Address":"7511 N SAN FERNANDO RD","BuildingArea":"20,240","PrimaryUseType":"Industrial","Jurisdiction":"LADBS","Size":"","Customer":"Edna Disiere","AuditLevel":"2","Audit Price":"$5,400.00"}
{"Address":"11640 Hart St","BuildingArea":"37,037","PrimaryUseType":"Industrial","Jurisdiction":"LADBS","Size":"","Customer":"Peter Bohlinger","AuditLevel":"2","Audit Price":"$6,000.00"}
{"Address":"9880 SAN FERNANDO RD","BuildingArea":"25,016","PrimaryUseType":"Light industrial","Jurisdiction":"LADBS","Size":"","Customer":"Chase Kinsley","AuditLevel":"2","Audit Price":"$5,400.00"}
{"Address":"7900 Haskell Ave","BuildingArea":"27,744","PrimaryUseType":"Light Industrial","Jurisdiction":"LADBS","Size":"","Customer":"Jessica Martinez","AuditLevel":"2","Audit Price":"$5,400.00"}
{"Address":"20650 Prairie St","BuildingArea":"101,772","PrimaryUseType":"Light industrial","Jurisdiction":"LADBS","Size":"","Customer":"Joseph / Carpalaid","AuditLevel":"2","Audit Price":"$8,900.00"}
{"Address":"5353 Grosvenor Blvd","BuildingArea":"103,655","PrimaryUseType":"Light Industrial","Jurisdiction":"LADBS","Size":"Extra Large","Customer":"Johnny Potts","AuditLevel":"2","Audit Price":"$8,900.00"}
{"Address":"3972 W 9TH St","BuildingArea":"28,564","PrimaryUseType":"Multifamily","Jurisdiction":"LADBS","Size":"","Customer":"Frances Barzakay","AuditLevel":"2","Audit Price":"$4,650.00"}
{"Address":"21909 LANARK ST","BuildingArea":"30,091","PrimaryUseType":"Multifamily","Jurisdiction":"LADBS","Size":"","Customer":"Fernanda","AuditLevel":"2","Audit Price":"$5,000.00"}
{"Address":"4343 TOLAND WAY","BuildingArea":"33,720","PrimaryUseType":"Multifamily","Jurisdiction":"LADBS","Size":"","Customer":"Michael Payne","AuditLevel":"2","Audit Price":"$5,000.00"}
{"Address":"1441 S Beverly Glen","BuildingArea":"41,859","PrimaryUseType":"Multifamily","Jurisdiction":"LADBS","Size":"","Customer":"Ross Denyer","AuditLevel":"2","Audit Price":"$5,350.00"}
{"Address":"5959 Franklin Ave","BuildingArea":"46,906","PrimaryUseType":"Multifamily","Jurisdiction":"LADBS","Size":"","Customer":"Vanessa","AuditLevel":"2","Audit Price":"$5,350.00"}
{"Address":"9640 Van Nuys Blvd","BuildingArea":"61,315","PrimaryUseType":"Multifamily","Jurisdiction":"LADBS","Size":"","Customer":"Margaret Essid","AuditLevel":"2","Audit Price":"$6,600.00"}
{"Address":"946 N MARIPOSA AVE","BuildingArea":"70,000","PrimaryUseType":"Multifamily","Jurisdiction":"LADBS","Size":"","Customer":"Daniel Brimco","AuditLevel":"2","Audit Price":"$6,750.00"}
{"Address":"6515 W SUNSET BLVD","BuildingArea":"21,142","PrimaryUseType":"Office","Jurisdiction":"LADBS","Size":"","Customer":"Allan Shamooilian","AuditLevel":"2","Audit Price":"$5,200.00"}
{"Address":"14546 HAMLIN St","BuildingArea":"24,723","PrimaryUseType":"Office","Jurisdiction":"LADBS","Size":"","Customer":"Frank Khalil","AuditLevel":"2","Audit Price":"$5,200.00"}
{"Address":"1500 S BROADWAY","BuildingArea":"39,445","PrimaryUseType":"Office","Jurisdiction":"LADBS","Size":"","Customer":"Ana / Venice Investments","AuditLevel":"2","Audit Price":"$5,550.00"}
{"Address":"5300 SANTA MONICA BLVD","BuildingArea":"58,377","PrimaryUseType":"Office","Jurisdiction":"LADBS","Size":"","Customer":"Lisa Willoughby","AuditLevel":"2","Audit Price":"$6,250.00"}
{"Address":"680 KNOX ST","BuildingArea":"59,739","PrimaryUseType":"Office","Jurisdiction":"LADBS","Size":"","Customer":"Janina Bates","AuditLevel":"2","Audit Price":"$6,250.00"}
{"Address":"5005 N EDENHURST AVE","BuildingArea":"291,046","PrimaryUseType":"Religious building","Jurisdiction":"LADBS","Size":"Extra Large","Customer":"David Jones","AuditLevel":"2","Audit Price":"$13,200.00"}
{"Address":"340 Mason St","BuildingArea":"14,761","PrimaryUseType":"Retail","Jurisdiction":"SF","Size":"Extra Small","Customer":"Michelle Sung","AuditLevel":"1","Audit Price":"$2,250.00"}
{"Address":"19783 RINALDI ST","BuildingArea":"23,940","PrimaryUseType":"Retail","Jurisdiction":"LADBS","Size":"","Customer":"Raoul Delgado","AuditLevel":"2","Audit Price":"$5,225.00"}
{"Address":"12833 Ventura Blvd","BuildingArea":"95,000","PrimaryUseType":"Retail","Jurisdiction":"LADBS","Size":"","Customer":"Demetrius Bradshaw","AuditLevel":"2","Audit Price":"$6,800.00"}
{"Address":"5711 Reseda Blvd","BuildingArea":"50,054","PrimaryUseType":"Senior Living/Multi-family","Jurisdiction":"LADBS","Size":"","Customer":"David Aguiniga","AuditLevel":"2","Audit Price":"$5,700.00"}
{"Address":"7447 SEPULVEDA BLVD","BuildingArea":"38,714","PrimaryUseType":"Senior Living/Multifamily","Jurisdiction":"LADBS","Size":"","Customer":"Engrid Scantlebury","AuditLevel":"2","Audit Price":"$5,000.00"}
{"Address":"840 S MISSION RD","BuildingArea":"21,898","PrimaryUseType":"Warehouse","Jurisdiction":"LADBS","Size":"","Customer":"Patti Costa","AuditLevel":"2","Audit Price":"$4,875.00"}
{"Address":"2290 S Centinela Ave","BuildingArea":"30,000","PrimaryUseType":"Warehouse","Jurisdiction":"LADBS","Size":"","Customer":"Kevin Moran","AuditLevel":"2","Audit Price":"$5,025.00"}
{"Address":"9601 CANOGA AVE","BuildingArea":"142,790","PrimaryUseType":"Warehouse","Jurisdiction":"LADBS","Size":"","Customer":"Ivan Cabrera","AuditLevel":"2","Audit Price":"$6,675.00"}
{"Address":"625 S St Andrew Pl","BuildingArea":"63,035","PrimaryUseType":"Religious building","Jurisdiction":"LADBS","Size":"","Customer":"Fernando Rios","AuditLevel":"2","Audit Price":"$5,400.00"}
{"Address":"320 N VERMONT AVE","BuildingArea":"25,100","PrimaryUseType":"Commercial/Retail","Jurisdiction":"LADBS","Size":"","Customer":"Horus Msemaje","AuditLevel":"2","Audit Price":"$5,225.00"}
{"Address":"1219 N VERMONT AVE","BuildingArea":"28,534","PrimaryUseType":"Commercial/Retail","Jurisdiction":"LADBS","Size":"","Customer":"Tiffany Addison","AuditLevel":"2","Audit Price":"$5,225.00"}
{"Address":"3520 N Broadway","BuildingArea":"29,401","PrimaryUseType":"Commercial/Retail","Jurisdiction":"LADBS","Size":"","Customer":"Allina Nazaryan","AuditLevel":"2","Audit Price":"$5,225.00"}
{"Address":"3400 W Washington Blvd","BuildingArea":"30,800","PrimaryUseType":"Industrial","Jurisdiction":"LADBS","Size":"","Customer":"Alex Kim","AuditLevel":"2","Audit Price":"$6,000.00"}
{"Address":"259 S LOS ANGELES","BuildingArea":"48,000","PrimaryUseType":"Industrial","Jurisdiction":"LADBS","Size":"","Customer":"Ken Lao","AuditLevel":"2","Audit Price":"$6,400.00"}
{"Address":"20730 DEARBORN ST","BuildingArea":"53,564","PrimaryUseType":"Industrial","Jurisdiction":"LADBS","Size":"","Customer":"Robert Fleischer","AuditLevel":"2","Audit Price":"$7,000.00"}
{"Address":"914 E 31st St","BuildingArea":"32,900","PrimaryUseType":"Light Industrial","Jurisdiction":"LADBS","Size":"","Customer":"David L Collier","AuditLevel":"2","Audit Price":"$5,100.00"}
{"Address":"125 S Ave 53","BuildingArea":"23,025","PrimaryUseType":"Multifamily","Jurisdiction":"LADBS","Size":"","Customer":"Gloria Diaz","AuditLevel":"2","Audit Price":"$4,650.00"}
{"Address":"1006 E 28TH  ST","BuildingArea":"32,409","PrimaryUseType":"Multifamily/Apartment","Jurisdiction":"LADBS","Size":"","Customer":"Jason Levine","AuditLevel":"2","Audit Price":"$5,000.00"}
{"Address":"4417 Hazeltine Ave","BuildingArea":"22,585","PrimaryUseType":"Multifamily/Apartment/Condos","Jurisdiction":"LADBS","Size":"","Customer":"Nina Kolesnik","AuditLevel":"2","Audit Price":"$4,650.00"}
{"Address":"4760 KESTER Ave","BuildingArea":"22,739","PrimaryUseType":"Multifamily/Apartment/Condos","Jurisdiction":"LADBS","Size":"","Customer":"Matthew Lichtenauer","AuditLevel":"2","Audit Price":"$4,650.00"}
{"Address":"13850 Victory Blvd","BuildingArea":"23,275","PrimaryUseType":"Multifamily/Apartment/Condos","Jurisdiction":"LADBS","Size":"","Customer":"Allina Nazaryan","AuditLevel":"2","Audit Price":"$4,650.00"}
{"Address":"4540 Hazeltine Ave","BuildingArea":"23,606","PrimaryUseType":"Multifamily/Apartment/Condos","Jurisdiction":"LADBS","Size":"","Customer":"Allina Nazaryan","AuditLevel":"2","Audit Price":"$4,650.00"}
{"Address":"9301 DARBY AVE","BuildingArea":"26,827","PrimaryUseType":"Multifamily/Apartment/Condos","Jurisdiction":"LADBS","Size":"","Customer":"Mr Iraj","AuditLevel":"2","Audit Price":"$4,650.00"}
{"Address":"805 S Mesa St","BuildingArea":"31,890","PrimaryUseType":"Multifamily/Apartment/Condos","Jurisdiction":"LADBS","Size":"","Customer":"Jason Levine","AuditLevel":"2","Audit Price":"$5,000.00"}
{"Address":"6530 Independence Ave","BuildingArea":"145,442","PrimaryUseType":"Multifamily/Apartment/Condos","Jurisdiction":"LADBS","Size":"","Customer":"Melizza/LA Apartments","AuditLevel":"2","Audit Price":"$12,000.00"}
{"Address":"10750 Ohio Avenue","BuildingArea":"22,154","PrimaryUseType":"Religious building","Jurisdiction":"LADBS","Size":"","Customer":"Lois Massey","AuditLevel":"2","Audit Price":"$4,700.00"}
{"Address":"3903 WILSHIRE BLVD","BuildingArea":"32,843","PrimaryUseType":"Religious building","Jurisdiction":"LADBS","Size":"","Customer":"Lauren Azeltine","AuditLevel":"2","Audit Price":"$5,200.00"}
{"Address":"452 N Western Ave (444 N Western Ave.)","BuildingArea":"41,377","PrimaryUseType":"Religious building","Jurisdiction":"LADBS","Size":"","Customer":"Nara Han","AuditLevel":"2","Audit Price":"$5,700.00"}
{"Address":"1662 LONG BEACH AVE","BuildingArea":"21,780","PrimaryUseType":"Warehouse","Jurisdiction":"LADBS","Size":"","Customer":"Zack Freitelberg","AuditLevel":"2","Audit Price":"$4,875.00"}
{"Address":"700 S HILL ST","BuildingArea":"67,000","PrimaryUseType":"Office","Jurisdiction":"LADBS","Size":"","Customer":"Maria Tandoy","AuditLevel":"2","Audit Price":"$6,600.00"}
{"Address":"311 Boyd St","BuildingArea":"32,315","PrimaryUseType":"Light Industrial","Jurisdiction":"LADBS","Size":"","Customer":"Juan Guerrero","AuditLevel":"2","Audit Price":"$5,100.00"}
{"Address":"617 S Olive St","BuildingArea":"99,019","PrimaryUseType":"Office","Jurisdiction":"LADBS","Size":"","Customer":"Michael Nielsen","AuditLevel":"2","Audit Price":"$7,650.00"}
{"Address":"8371 CANOGA AVE","BuildingArea":"23,160","PrimaryUseType":"warehouse","Jurisdiction":"LADBS","Size":"","Customer":"Michael Bolger","AuditLevel":"2","Audit Price":"$4,875.00"}
{"Address":"8150 Beverly Blvd","BuildingArea":"21,073","PrimaryUseType":"Commercial/Retail","Jurisdiction":"LADBS","Size":"","Customer":"Mahmoud AlAlusi","AuditLevel":"2","Audit Price":"$5,225.00"}
{"Address":"6505 Hollywood Blvd","BuildingArea":"23,998","PrimaryUseType":"Commercial/Retail","Jurisdiction":"LADBS","Size":"","Customer":"Ricardo Salinas","AuditLevel":"2","Audit Price":"$5,225.00"}
{"Address":"629 S BROADWAY","BuildingArea":"56,096","PrimaryUseType":"Commercial/Retail","Jurisdiction":"LADBS","Size":"","Customer":"Neshan kahkejian","AuditLevel":"2","Audit Price":"$5,900.00"}
{"Address":"609 E 5TH ST","BuildingArea":"27,500","PrimaryUseType":"Hotel","Jurisdiction":"LADBS","Size":"","Customer":"Rodrigo Castellanos","AuditLevel":"2","Audit Price":"$4,800.00"}
{"Address":"19200 HARBORGATE WAY","BuildingArea":"52,932","PrimaryUseType":"Hotel","Jurisdiction":"LADBS","Size":"","Customer":"Tracy Patti","AuditLevel":"2","Audit Price":"$5,750.00"}
{"Address":"2835 E WASHINGTON BLVD","BuildingArea":"21,457","PrimaryUseType":"Industrial","Jurisdiction":"LADBS","Size":"","Customer":"Veronica Garcia","AuditLevel":"2","Audit Price":"$5,400.00"}
{"Address":"15001 Calvert St","BuildingArea":"22,200","PrimaryUseType":"Industrial","Jurisdiction":"LADBS","Size":"","Customer":"Bill Reider","AuditLevel":"2","Audit Price":"$5,200.00"}
{"Address":"16641 ROSCOE PL","BuildingArea":"24,870","PrimaryUseType":"Industrial","Jurisdiction":"LADBS","Size":"","Customer":"Magd Keram","AuditLevel":"2","Audit Price":"$5,400.00"}
{"Address":"7361 Ethel Ave","BuildingArea":"30,000","PrimaryUseType":"Industrial","Jurisdiction":"LADBS","Size":"","Customer":"Shannon Turner","AuditLevel":"2","Audit Price":"$6,000.00"}
{"Address":"10643 GLENOAKS BLVD","BuildingArea":"38,063","PrimaryUseType":"Industrial","Jurisdiction":"LADBS","Size":"","Customer":"Rennie Suarez","AuditLevel":"2","Audit Price":"$6,000.00"}
{"Address":"9600 DE SOTO AVE","BuildingArea":"36,637","PrimaryUseType":"Light Industrial","Jurisdiction":"LADBS","Size":"","Customer":"Russell Crossley","AuditLevel":"2","Audit Price":"$5,100.00"}
{"Address":"1426 W 224TH ST","BuildingArea":"20,649","PrimaryUseType":"Multi-famiy","Jurisdiction":"LADBS","Size":"","Customer":"Rachel Cardenas","AuditLevel":"2","Audit Price":"$4,650.00"}
{"Address":"3035 W 15TH ST","BuildingArea":"21,756","PrimaryUseType":"Multi-famiy","Jurisdiction":"LADBS","Size":"","Customer":"Rachel Cardenas","AuditLevel":"2","Audit Price":"$4,650.00"}
{"Address":"3851 COCO AVE ","BuildingArea":"21,768","PrimaryUseType":"Multi-famiy","Jurisdiction":"LADBS","Size":"","Customer":"Rachel Cardenas","AuditLevel":"2","Audit Price":"$4,650.00"}
{"Address":"661 SHATTO PL ","BuildingArea":"24,000","PrimaryUseType":"Multi-famiy","Jurisdiction":"LADBS","Size":"","Customer":"Rachel Cardenas","AuditLevel":"2","Audit Price":"$4,650.00"}
{"Address":"3311 ROWENA AVE","BuildingArea":"24,610","PrimaryUseType":"Multi-famiy","Jurisdiction":"LADBS","Size":"","Customer":"Rachel Cardenas","AuditLevel":"2","Audit Price":"$4,650.00"}
{"Address":"1050 S WESTMORELAND AVE","BuildingArea":"25,525","PrimaryUseType":"Multi-famiy","Jurisdiction":"LADBS","Size":"","Customer":"Rachel Cardenas","AuditLevel":"2","Audit Price":"$4,650.00"}
{"Address":"12047 CALIFA ST","BuildingArea":"28,398","PrimaryUseType":"Multi-famiy","Jurisdiction":"LADBS","Size":"","Customer":"Rachel Cardenas","AuditLevel":"2","Audit Price":"$4,650.00"}
{"Address":"260 S AVENUE 54","BuildingArea":"30,738","PrimaryUseType":"Multi-famiy","Jurisdiction":"LADBS","Size":"","Customer":"Rachel Cardenas","AuditLevel":"2","Audit Price":"$5,000.00"}
{"Address":"519 S GRAMERCY PL","BuildingArea":"30,866","PrimaryUseType":"Multi-famiy","Jurisdiction":"LADBS","Size":"","Customer":"Rachel Cardenas","AuditLevel":"2","Audit Price":"$5,000.00"}
{"Address":"4770 KESTER AVE","BuildingArea":"45,832","PrimaryUseType":"Multi-famiy","Jurisdiction":"LADBS","Size":"","Customer":"Rachel Cardenas","AuditLevel":"2","Audit Price":"$5,350.00"}
{"Address":"5712 LAUREL CANYON BLVD","BuildingArea":"60,360","PrimaryUseType":"Multi-famiy","Jurisdiction":"LADBS","Size":"","Customer":"Rachel Cardenas","AuditLevel":"2","Audit Price":"$6,000.00"}
{"Address":"6101 CLYBOURN AVE","BuildingArea":"75,960","PrimaryUseType":"Multi-famiy","Jurisdiction":"LADBS","Size":"","Customer":"Rachel Cardenas","AuditLevel":"2","Audit Price":"$6,750.00"}
{"Address":"15061 ARCHWOOD ST","BuildingArea":"21,000","PrimaryUseType":"Multifamily/Apartment/Condos","Jurisdiction":"LADBS","Size":"","Customer":"Alex Weiss","AuditLevel":"2","Audit Price":"$4,650.00"}
{"Address":"9147 VAN NUYS BLVD","BuildingArea":"21,404","PrimaryUseType":"Multifamily/Apartment/Condos","Jurisdiction":"LADBS","Size":"","Customer":"Dalia Bastidas","AuditLevel":"2","Audit Price":"$4,650.00"}
{"Address":"4353 W 5th St","BuildingArea":"21,829","PrimaryUseType":"Multifamily/Apartment/Condos","Jurisdiction":"LADBS","Size":"","Customer":"Ryan Stitzel","AuditLevel":"2","Audit Price":"$4,650.00"}
{"Address":"5225 Lexington Ave","BuildingArea":"22,210","PrimaryUseType":"Multifamily/Apartment/Condos","Jurisdiction":"LADBS","Size":"","Customer":"Daniel Brimco","AuditLevel":"2","Audit Price":"$4,650.00"}
{"Address":"5545 Carlton Way ","BuildingArea":"26,400","PrimaryUseType":"Multifamily/Apartment/Condos","Jurisdiction":"LADBS","Size":"","Customer":"Daniel Brimco","AuditLevel":"2","Audit Price":"$4,650.00"}
{"Address":"11939 Albers St","BuildingArea":"27,565","PrimaryUseType":"Multifamily/Apartment/Condos","Jurisdiction":"LADBS","Size":"","Customer":"Gidon Rosman","AuditLevel":"2","Audit Price":"$4,650.00"}
{"Address":"820 S. Burlington Ave.","BuildingArea":"27,966","PrimaryUseType":"Multifamily/Apartment/Condos","Jurisdiction":"LADBS","Size":"","Customer":"Estrella Perez / Solari Enterprises, Inc.","AuditLevel":"2","Audit Price":"$4,650.00"}
{"Address":"1500 JAMES M WOOD BLVD","BuildingArea":"28,248","PrimaryUseType":"Multifamily/Apartment/Condos","Jurisdiction":"LADBS","Size":"","Customer":"Nathan Korman","AuditLevel":"2","Audit Price":"$4,650.00"}
{"Address":"12711 Moorpark Street","BuildingArea":"30,604","PrimaryUseType":"Multifamily/Apartment/Condos","Jurisdiction":"LADBS","Size":"","Customer":"Chris O'Connell","AuditLevel":"2","Audit Price":"$5,000.00"}
{"Address":"7777 Hollywood Blvd","BuildingArea":"33,369","PrimaryUseType":"Multifamily/Apartment/Condos","Jurisdiction":"LADBS","Size":"","Customer":"Michael East","AuditLevel":"2","Audit Price":"$5,000.00"}
{"Address":"350 S Reno St","BuildingArea":"38,612","PrimaryUseType":"Multifamily/Apartment/Condos","Jurisdiction":"LADBS","Size":"","Customer":"Marilu Vargas","AuditLevel":"2","Audit Price":"$5,000.00"}
{"Address":"10965 WELLWORTH AVE","BuildingArea":"59,455","PrimaryUseType":"Multifamily/Apartment/Condos","Jurisdiction":"LADBS","Size":"","Customer":"Lilliana De La O","AuditLevel":"2","Audit Price":"$5,700.00"}
{"Address":"860 West 5th Street","BuildingArea":"60,840","PrimaryUseType":"Multifamily/Apartment/Condos","Jurisdiction":"LADBS","Size":"","Customer":"Jesse Alvarez","AuditLevel":"2","Audit Price":"$6,000.00"}
{"Address":"571 S CORONADO ST","BuildingArea":"62,826","PrimaryUseType":"Multifamily/Apartment/Condos","Jurisdiction":"LADBS","Size":"","Customer":"Judy Garcia","AuditLevel":"2","Audit Price":"$6,000.00"}
{"Address":"247 S. Ave. 50","BuildingArea":"63,766","PrimaryUseType":"Multifamily/Apartment/Condos","Jurisdiction":"LADBS","Size":"","Customer":"Estrella Perez / Solari Enterprises, Inc.","AuditLevel":"2","Audit Price":"$6,000.00"}
{"Address":"11330 Otsego Street","BuildingArea":"68,228","PrimaryUseType":"Multifamily/Apartment/Condos","Jurisdiction":"LADBS","Size":"","Customer":"Jason Levine","AuditLevel":"2","Audit Price":"$6,000.00"}
{"Address":"2345 W MERTON AVE","BuildingArea":"81,000","PrimaryUseType":"Multifamily/Apartment/Condos","Jurisdiction":"LADBS","Size":"","Customer":"Donna Hall","AuditLevel":"2","Audit Price":"$7,500.00"}
{"Address":"7950 West Sunset Blvd","BuildingArea":"232,540","PrimaryUseType":"Multifamily/Apartment/Condos","Jurisdiction":"LADBS","Size":"","Customer":"Phil Schector","AuditLevel":"2","Audit Price":"$13,500.00"}
{"Address":"801 S Hope St","BuildingArea":"300,000","PrimaryUseType":"Multifamily/Apartment/Condos","Jurisdiction":"LADBS","Size":"","Customer":"Firas Aboulhosn","AuditLevel":"2","Audit Price":"$13,500.00"}
{"Address":"11565 Laurel Canyon Blvd","BuildingArea":"20,478","PrimaryUseType":"Office","Jurisdiction":"LADBS","Size":"","Customer":"Martin Titizian","AuditLevel":"2","Audit Price":"$5,200.00"}
{"Address":"3301 BARHAM BLVD","BuildingArea":"25,848","PrimaryUseType":"Office","Jurisdiction":"LADBS","Size":"","Customer":"Christine Kabealo","AuditLevel":"2","Audit Price":"$5,200.00"}
{"Address":"16800 Devonshire St","BuildingArea":"29,000","PrimaryUseType":"Office","Jurisdiction":"LADBS","Size":"","Customer":"Albert Cohen","AuditLevel":"2","Audit Price":"$5,200.00"}
{"Address":"15490 Ventura Blvd","BuildingArea":"43,000","PrimaryUseType":"Office","Jurisdiction":"LADBS","Size":"","Customer":"Albert Cohen","AuditLevel":"2","Audit Price":"$5,900.00"}
{"Address":"19191 S VERMONT AVE","BuildingArea":"237,145","PrimaryUseType":"Office","Jurisdiction":"LADBS","Size":"","Customer":"Janelle Hjelmstad","AuditLevel":"2","Audit Price":"$11,500.00"}
{"Address":"5429 Lindley Ave","BuildingArea":"136,721","PrimaryUseType":"Religious/Church","Jurisdiction":"LADBS","Size":"","Customer":"Eddie Garcia","AuditLevel":"2","Audit Price":"$7,975.00"}
{"Address":"1425 N Naud St","BuildingArea":"31,536","PrimaryUseType":"Warehouse","Jurisdiction":"LADBS","Size":"","Customer":"Yan Wong","AuditLevel":"2","Audit Price":"$5,025.00"}
{"Address":"20822-20832 Dearborn St","BuildingArea":"34,176","PrimaryUseType":"Warehouse","Jurisdiction":"LADBS","Size":"","Customer":"Jim Zafrani","AuditLevel":"2","Audit Price":"$5,025.00"}
{"Address":"1450 Mirasol St ","BuildingArea":"78,472","PrimaryUseType":"Warehouse","Jurisdiction":"LADBS","Size":"","Customer":"Gabriela Marquez","AuditLevel":"2","Audit Price":"$5,625.00"}
{"Address":"112 W 52nd St","BuildingArea":"28,215","PrimaryUseType":"Religious/Church","Jurisdiction":"LADBS","Size":"","Customer":"Rodney Ross","AuditLevel":"2","Audit Price":"$4,700.00"}
{"Address":"606 S Olive St","BuildingArea":"283,251","PrimaryUseType":"Office","Jurisdiction":"LADBS","Size":"","Customer":"Jennifer Chun","AuditLevel":"2","Audit Price":"$13,500.00"}
{"Address":"1020 S FAIRFAX AVE","BuildingArea":"23,848","PrimaryUseType":"hospital/private","Jurisdiction":"LADBS","Size":"","Customer":"Isani Baltazar","AuditLevel":"2","Audit Price":"$6,350.00"}
{"Address":"3221 S Hill St","BuildingArea":"20,545","PrimaryUseType":"Industrial","Jurisdiction":"LADBS","Size":"","Customer":"David / The Hill Studios LLC","AuditLevel":"2","Audit Price":"$5,200.00"}
{"Address":"8966 MASON AVE","BuildingArea":"44,080","PrimaryUseType":"Industrial","Jurisdiction":"LADBS","Size":"","Customer":"Gary Hu","AuditLevel":"2","Audit Price":"$3,800.00"}
{"Address":"846 E 60TH ST","BuildingArea":"22,750","PrimaryUseType":"Light Industrial","Jurisdiction":"LADBS","Size":"","Customer":"Bonnie Kim","AuditLevel":"2","Audit Price":"$5,200.00"}
{"Address":"5756 ALBA ST","BuildingArea":"23,324","PrimaryUseType":"Light Industrial","Jurisdiction":"LADBS","Size":"","Customer":"Steven Peterson","AuditLevel":"2","Audit Price":"$5,200.00"}
{"Address":"10871 La Tuna Canyon Rd","BuildingArea":"39,640","PrimaryUseType":"Light Industrial","Jurisdiction":"LADBS","Size":"","Customer":"Jack Kerimian","AuditLevel":"2","Audit Price":"$6,000.00"}
{"Address":"20409 Prairie St","BuildingArea":"40,001","PrimaryUseType":"Light Industrial","Jurisdiction":"LADBS","Size":"","Customer":"Prosith Khiev","AuditLevel":"2","Audit Price":"$6,400.00"}
{"Address":"510 S Normandie Ave","BuildingArea":"27,477","PrimaryUseType":"Multifamily/Apartment/Condos","Jurisdiction":"LADBS","Size":"","Customer":"Lilliana De La O","AuditLevel":"2","Audit Price":"$4,650.00"}
{"Address":"2640 MENLO AVE","BuildingArea":"32,035","PrimaryUseType":"Multifamily/Apartment/Condos","Jurisdiction":"LADBS","Size":"","Customer":"Ron Salvame","AuditLevel":"2","Audit Price":"$5,000.00"}
{"Address":"4020 MARATHON ST","BuildingArea":"43,456","PrimaryUseType":"Multifamily/Apartment/Condos","Jurisdiction":"LADBS","Size":"","Customer":"Anna Ruiz","AuditLevel":"2","Audit Price":"$5,350.00"}
{"Address":"1050 Mariposa Ave","BuildingArea":"59,246","PrimaryUseType":"Multifamily/Apartment/Condos","Jurisdiction":"LADBS","Size":"","Customer":"Christopher French","AuditLevel":"2","Audit Price":"$5,700.00"}
{"Address":"930 S BONNIE BRAE ST","BuildingArea":"67,376","PrimaryUseType":"Multifamily/Apartment/Condos","Jurisdiction":"LADBS","Size":"","Customer":"Lilliana De La O","AuditLevel":"2","Audit Price":"$6,000.00"}
{"Address":"600 S RIDGELEY DR","BuildingArea":"83,000","PrimaryUseType":"Multifamily/Apartment/Condos","Jurisdiction":"LADBS","Size":"","Customer":"Gina Lugo","AuditLevel":"2","Audit Price":"$7,500.00"}
{"Address":"1711 S Central Ave","BuildingArea":"31,628","PrimaryUseType":"Warehouse","Jurisdiction":"LADBS","Size":"","Customer":"Ramin Simantob","AuditLevel":"2","Audit Price":"$5,025.00"}
{"Address":"810 E PICO BLVD","BuildingArea":"148,147","PrimaryUseType":"Commercial","Jurisdiction":"LADBS","Size":"","Customer":"Jino Kim","AuditLevel":"2","Audit Price":"$7,925.00"}
{"Address":"411 O'Farrell St","BuildingArea":"41,610","PrimaryUseType":"Hotel","Jurisdiction":"SF","Size":"","Customer":"Sandra Nkholise","AuditLevel":"1","Audit Price":"$2,750.00"}
{"Address":"7837 Deering Ave","BuildingArea":"20,200","PrimaryUseType":"Light Industrial","Jurisdiction":"LADBS","Size":"","Customer":"Gary / GAASI LLC","AuditLevel":"2","Audit Price":"$5,200.00"}
{"Address":"1101 S Hill St","BuildingArea":"81,993","PrimaryUseType":"Light Industrial","Jurisdiction":"LADBS","Size":"","Customer":"Alvin Poon","AuditLevel":"2","Audit Price":"$7,400.00"}
{"Address":"7347 HASKELL AVE","BuildingArea":"23,486","PrimaryUseType":"Multifamily/Apartment/Condos","Jurisdiction":"LADBS","Size":"","Customer":"Derek Karpel","AuditLevel":"2","Audit Price":"$4,650.00"}
{"Address":"420 S. Harvard Blvd","BuildingArea":"24,691","PrimaryUseType":"Multifamily/Apartment/Condos","Jurisdiction":"LADBS","Size":"","Customer":"Jino Kim","AuditLevel":"2","Audit Price":"$4,650.00"}
{"Address":"1054 S Bedford St","BuildingArea":"30,867","PrimaryUseType":"Multifamily/Apartment/Condos","Jurisdiction":"LADBS","Size":"","Customer":"Michael East","AuditLevel":"2","Audit Price":"$5,000.00"}
{"Address":"7215 HILLSIDE AVE","BuildingArea":"46,738","PrimaryUseType":"Multifamily/Apartment/Condos","Jurisdiction":"LADBS","Size":"","Customer":"Nick Eliopoulos","AuditLevel":"2","Audit Price":"$5,350.00"}
{"Address":"7224 HILLSIDE AVE","BuildingArea":"47,832","PrimaryUseType":"Multifamily/Apartment/Condos","Jurisdiction":"LADBS","Size":"","Customer":"Nick Eliopoulos","AuditLevel":"2","Audit Price":"$5,350.00"}
{"Address":"3348 WILSHIRE BLVD","BuildingArea":"184,681","PrimaryUseType":"Multifamily/Apartment/Condos","Jurisdiction":"LADBS","Size":"","Customer":"Regina Cho","AuditLevel":"2","Audit Price":"$12,000.00"}
{"Address":"20335 Ventura Blvd","BuildingArea":"57,600","PrimaryUseType":"Office","Jurisdiction":"LADBS","Size":"","Customer":"Ramin Shaygan","AuditLevel":"2","Audit Price":"$6,250.00"}